LICENSE
MANIFEST.in
README.md
requirements.txt
setup.py
BindingGP.egg-info/PKG-INFO
BindingGP.egg-info/SOURCES.txt
BindingGP.egg-info/dependency_links.txt
BindingGP.egg-info/requires.txt
BindingGP.egg-info/top_level.txt
bgp/__init__.py
bgp/base.py
bgp/flow.py
bgp/gp.py
bgp/postprocess.py
bgp/preprocess.py
bgp/skflow.py
bgp/calculation/__init__.py
bgp/calculation/coefficient.py
bgp/calculation/scores.py
bgp/calculation/translate.py
bgp/functions/__init__.py
bgp/functions/dimfunc.py
bgp/functions/gsymfunc.py
bgp/functions/newfunc.py
bgp/functions/npfunc.py
bgp/functions/symfunc.py
bgp/iteration/__init__.py
bgp/iteration/newpoints.py
bgp/iteration/nonewpoints.py
bgp/probability/__init__.py
bgp/probability/preference.py
test/test2.py
test/test_der.py
test/test_dim.py
test/test_function.py
test/test_one_sample.py
test/test_preference.py
test/test_score.py
test/test_simp.py
test/test_symbol_base.py
test/test_symbol_gp.py
test/test_translate.py